README.md
setup.cfg
setup.py
topsis_101703250_COE12/tops.py
topsis_101703250_COE12.egg-info/PKG-INFO
topsis_101703250_COE12.egg-info/SOURCES.txt
topsis_101703250_COE12.egg-info/dependency_links.txt
topsis_101703250_COE12.egg-info/entry_points.txt
topsis_101703250_COE12.egg-info/requires.txt
topsis_101703250_COE12.egg-info/top_level.txt